[{"no": "K1092", "startStation": "福州", "endStation": "南京", "startTime": "07:03", "duration": "19时30分", "price": 152.5}, {"no": "G56", "startStation": "福州", "endStation": "南京南", "startTime": "07:53", "duration": "6时26分", "price": 388.5}, {"no": "D3236", "startStation": "福州南", "endStation": "南京南", "startTime": "08:18", "duration": "6时26分", "price": 320.0}, {"no": "D3142", "startStation": "福州南", "endStation": "南京", "startTime": "09:42", "duration": "8时20分", "price": 438.0}, {"no": "G1676", "startStation": "福州", "endStation": "南京南", "startTime": "10:22", "duration": "5时27分", "price": 410.0}, {"no": "D3136", "startStation": "福州南", "endStation": "南京南", "startTime": "11:26", "duration": "8时54分", "price": 442.0}, {"no": "D3296", "startStation": "福州南", "endStation": "南京南", "startTime": "11:31", "duration": "7时8分", "price": 363.0}, {"no": "D2294", "startStation": "福州南", "endStation": "南京南", "startTime": "13:16", "duration": "6时26分", "price": 363.0}, {"no": "D2282", "startStation": "福州南", "endStation": "南京南", "startTime": "14:41", "duration": "8时40分", "price": 442.0}, {"no": "G1662", "startStation": "福州", "endStation": "南京南", "startTime": "15:09", "duration": "5时38分", "price": 410.0}, {"no": "D3240", "startStation": "福州", "endStation": "南京南", "startTime": "15:56", "duration": "6时51分", "price": 363.0}, {"no": "G1668", "startStation": "福州", "endStation": "南京南", "startTime": "17:24", "duration": "5时12分", "price": 410.0}]